setup.py
django_tumblelog.egg-info/PKG-INFO
django_tumblelog.egg-info/SOURCES.txt
django_tumblelog.egg-info/dependency_links.txt
django_tumblelog.egg-info/requires.txt
django_tumblelog.egg-info/top_level.txt
tumblelog/__init__.py
tumblelog/actions.py
tumblelog/admin.py
tumblelog/choices.py
tumblelog/fields.py
tumblelog/filters.py
tumblelog/managers.py
tumblelog/mixins.py
tumblelog/models.py
tumblelog/settings.py
tumblelog/urls.py
tumblelog/util.py
tumblelog/views.py
tumblelog/contrib/__init__.py
tumblelog/contrib/audio.py
tumblelog/contrib/code.py
tumblelog/contrib/file.py
tumblelog/contrib/link.py
tumblelog/contrib/photo.py
tumblelog/contrib/text.py
tumblelog/contrib/twitter.py
tumblelog/contrib/video.py
tumblelog/migrations/0001_initial.py
tumblelog/migrations/__init__.py