Metadata-Version: 1.0
Name: django-tumblelog
Version: 0.1
Summary: A simple and extensible tumblelog engine for Django
Home-page: https://github.com/chuckharmston/django-tumblelog
Author: Chuck Harmston
Author-email: chuck@chuckharmston.com
License: MIT
Keywords: django,blog,tumblelog,tumblr
Platform: UNKNOWN
Classifier: Development Status :: 4 - Beta
Classifier: Environment :: Web Environment
Classifier: Framework :: Django
Classifier: Intended Audience :: Developers
Classifier: Intended Audience :: End Users/Desktop
Classifier: License :: OSI Approved :: MIT License
Classifier: Natural Language :: English
Classifier: Operating System :: OS Independent
Classifier: Programming Language :: Python
Classifier: Topic :: Communications
Classifier: Topic :: Internet :: WWW/HTTP :: Dynamic Content :: News/Diary
